ShejiaoMeitiWajueChuyi/README.md
ShejiaoMeitiWajueChuyi/__init__.py
ShejiaoMeitiWajueChuyi/__main__.py
ShejiaoMeitiWajueChuyi/file.epub
ShejiaoMeitiWajueChuyi/index.html
ShejiaoMeitiWajueChuyi/css/__init__.py
ShejiaoMeitiWajueChuyi/css/annotations.css
ShejiaoMeitiWajueChuyi/css/main.css
ShejiaoMeitiWajueChuyi/css/normalize.css
ShejiaoMeitiWajueChuyi/css/popup.css
ShejiaoMeitiWajueChuyi/font/__init__.py
ShejiaoMeitiWajueChuyi/font/fontello.eot
ShejiaoMeitiWajueChuyi/font/fontello.svg
ShejiaoMeitiWajueChuyi/font/fontello.ttf
ShejiaoMeitiWajueChuyi/font/fontello.woff
ShejiaoMeitiWajueChuyi/img/__init__.py
ShejiaoMeitiWajueChuyi/img/annotator-glyph-sprite.png
ShejiaoMeitiWajueChuyi/img/annotator-icon-sprite.png
ShejiaoMeitiWajueChuyi/img/apple-touch-icon.png
ShejiaoMeitiWajueChuyi/img/cancelfullscreen.png
ShejiaoMeitiWajueChuyi/img/close.png
ShejiaoMeitiWajueChuyi/img/fullscreen.png
ShejiaoMeitiWajueChuyi/img/loader.gif
ShejiaoMeitiWajueChuyi/img/menu-icon.png
ShejiaoMeitiWajueChuyi/img/save.png
ShejiaoMeitiWajueChuyi/img/saved.png
ShejiaoMeitiWajueChuyi/img/settings-s.png
ShejiaoMeitiWajueChuyi/img/settings.png
ShejiaoMeitiWajueChuyi/img/star.png
ShejiaoMeitiWajueChuyi/js/__init__.py
ShejiaoMeitiWajueChuyi/js/epub.js
ShejiaoMeitiWajueChuyi/js/epub.min.js
ShejiaoMeitiWajueChuyi/js/epub.min.map
ShejiaoMeitiWajueChuyi/js/hooks.min.js
ShejiaoMeitiWajueChuyi/js/hooks.min.map
ShejiaoMeitiWajueChuyi/js/reader.js
ShejiaoMeitiWajueChuyi/js/reader.js.map
ShejiaoMeitiWajueChuyi/js/reader.min.js
ShejiaoMeitiWajueChuyi/js/reader.min.map
ShejiaoMeitiWajueChuyi/js/hooks/__init__.py
ShejiaoMeitiWajueChuyi/js/hooks/extensions/__init__.py
ShejiaoMeitiWajueChuyi/js/hooks/extensions/highlight.js
ShejiaoMeitiWajueChuyi/js/libs/__init__.py
ShejiaoMeitiWajueChuyi/js/libs/jquery.min.js
ShejiaoMeitiWajueChuyi/js/libs/localforage.min.js
ShejiaoMeitiWajueChuyi/js/libs/screenfull.js
ShejiaoMeitiWajueChuyi/js/libs/screenfull.min.js
ShejiaoMeitiWajueChuyi/js/libs/zip.min.js
shejiao_meiti_wajue_chuyi-2024.3.5.0.dist-info/METADATA
shejiao_meiti_wajue_chuyi-2024.3.5.0.dist-info/WHEEL
shejiao_meiti_wajue_chuyi-2024.3.5.0.dist-info/entry_points.txt
shejiao_meiti_wajue_chuyi-2024.3.5.0.dist-info/top_level.txt
shejiao_meiti_wajue_chuyi-2024.3.5.0.dist-info/RECORD
